youtrack_rocket_mcp/__init__.py
youtrack_rocket_mcp/_version.py
youtrack_rocket_mcp/config.py
youtrack_rocket_mcp/server.py
youtrack_rocket_mcp/api/__init__.py
youtrack_rocket_mcp/api/client.py
youtrack_rocket_mcp/api/field_cache.py
youtrack_rocket_mcp/api/schemas.py
youtrack_rocket_mcp/api/types.py
youtrack_rocket_mcp/api/resources/__init__.py
youtrack_rocket_mcp/api/resources/issues.py
youtrack_rocket_mcp/api/resources/projects.py
youtrack_rocket_mcp/api/resources/search.py
youtrack_rocket_mcp/api/resources/users.py
youtrack_rocket_mcp/tools/__init__.py
youtrack_rocket_mcp/tools/issues.py
youtrack_rocket_mcp/tools/projects.py
youtrack_rocket_mcp/tools/search.py
youtrack_rocket_mcp/tools/search_guide.py
youtrack_rocket_mcp/tools/users.py
youtrack_rocket_mcp/utils/__init__.py
youtrack_rocket_mcp/utils/period_parser.py
youtrack_rocket_mcp-0.4.7.dist-info/METADATA
youtrack_rocket_mcp-0.4.7.dist-info/WHEEL
youtrack_rocket_mcp-0.4.7.dist-info/entry_points.txt
youtrack_rocket_mcp-0.4.7.dist-info/licenses/LICENSE
youtrack_rocket_mcp-0.4.7.dist-info/RECORD
