Metadata-Version: 2.4
Name: youtrack-rocket-mcp
Version: 0.4.7
Summary: 🚀 Lightning-fast Model Context Protocol (MCP) server for YouTrack issue tracking system
Author-email: Ilya Volnistov <ivolnistov@gmail.com>
License: MIT
License-File: LICENSE
Keywords: api,async,fast,integration,issue-tracking,mcp,rocket,youtrack
Classifier: Development Status :: 4 - Beta
Classifier: Intended Audience :: Developers
Classifier: License :: OSI Approved :: MIT License
Classifier: Programming Language :: Python :: 3
Classifier: Programming Language :: Python :: 3.12
Classifier: Topic :: Software Development :: Libraries
Classifier: Topic :: Software Development :: Libraries :: Python Modules
Requires-Python: >=3.12
Requires-Dist: fastmcp>=0.1.0
Requires-Dist: httpx>=0.24.0
Requires-Dist: pydantic>=2.0.0
